{
    "mipEra": "cmip6", 
    "institute": "mri", 
    "seedingSource": "cmip5:mri-esm1", 
    "sourceID": "mri-esm2-0", 
    "topic": "atmos", 
    "content": {
        "cmip6.atmos.cloud_scheme.overview": {
            "values": [
                "Cloud Scheme Attributes / Cloud Overlap : \r\n     other means  maximum-random for LW, random for SW."
            ]
        }, 
        "cmip6.atmos.cloud_scheme.sub_grid_scale_water_distribution.convection_coupling": {
            "values": [
                "coupled with deep", 
                "coupled with shallow"
            ]
        }, 
        "cmip6.atmos.cloud_scheme.sub_grid_scale_water_distribution.function_name": {
            "values": [
                "Uniform"
            ]
        }, 
        "cmip6.atmos.cloud_scheme.sub_grid_scale_water_distribution.function_order": {
            "values": [
                2
            ]
        }, 
        "cmip6.atmos.cloud_scheme.sub_grid_scale_water_distribution.type": {
            "values": [
                "prognostic"
            ]
        }, 
        "cmip6.atmos.cloud_scheme.uses_separate_treatment": {
            "values": [
                "Yes"
            ]
        }, 
        "cmip6.atmos.dynamical_core.advection.tracers.conservation_method": {
            "values": [
                "conservation fixer"
            ]
        }, 
        "cmip6.atmos.dynamical_core.advection.tracers.conserved_quantities": {
            "values": [
                "Other: total mass, water vapour, cloud water and tracers"
            ]
        }, 
        "cmip6.atmos.dynamical_core.advection.tracers.scheme_characteristics": {
            "values": [
                "semi-Lagrangian"
            ]
        }, 
        "cmip6.atmos.dynamical_core.diffusion_horizontal.scheme_name": {
            "values": [
                "Bi-harmonic diffusion"
            ]
        }, 
        "cmip6.atmos.dynamical_core.overview": {
            "values": [
                "Time Stepping Framework / Scheme Type : semi-implicit semi-Lagrangian\r\nHorizontal Diffusion / Scheme Method : bi-harmonic diffusion\r\n(MEMO: in kakushin     prognostic   vapour, cloud water (liquid+solid) )"
            ]
        }, 
        "cmip6.atmos.dynamical_core.prognostic_variables": {
            "values": [
                "clouds", 
                "surface pressure", 
                "temperature", 
                "water ice", 
                "water liquid", 
                "water vapour", 
                "wind components"
            ]
        }, 
        "cmip6.atmos.dynamical_core.timestepping_type": {
            "values": [
                "semi-implicit"
            ]
        }, 
        "cmip6.atmos.dynamical_core.top_boundary.top_boundary_condition": {
            "values": [
                "sponge layer"
            ]
        }, 
        "cmip6.atmos.dynamical_core.top_boundary.top_heat": {
            "values": [
                "0.01hPa"
            ]
        }, 
        "cmip6.atmos.dynamical_core.top_boundary.top_wind": {
            "values": [
                "0.01hPa"
            ]
        }, 
        "cmip6.atmos.gravity_waves.orographic_gravity_waves.calculation_method": {
            "values": [
                "non-linear calculation"
            ]
        }, 
        "cmip6.atmos.gravity_waves.orographic_gravity_waves.propagation_scheme": {
            "values": [
                "linear theory"
            ]
        }, 
        "cmip6.atmos.gravity_waves.orographic_gravity_waves.source_mechanisms": {
            "values": [
                "statistical sub-grid scale variance"
            ]
        }, 
        "cmip6.atmos.gravity_waves.subgrid_scale_orography": {
            "values": [
                "effect on drag"
            ]
        }, 
        "cmip6.atmos.grid.discretisation.horizontal.scheme_type": {
            "values": [
                "spectral"
            ]
        }, 
        "cmip6.atmos.key_properties.basic_approximations": {
            "values": [
                "hydrostatic", 
                "primitive equations"
            ]
        }, 
        "cmip6.atmos.key_properties.model_family": {
            "values": [
                "AGCM"
            ]
        }, 
        "cmip6.atmos.key_properties.name": {
            "values": [
                "MRI-AGCM3.3"
            ]
        }, 
        "cmip6.atmos.key_properties.orography.type": {
            "values": [
                "Other: present day"
            ]
        }, 
        "cmip6.atmos.key_properties.timestepping.timestep_dynamics": {
            "values": [
                1800
            ]
        }, 
        "cmip6.atmos.microphysics_precipitation.large_scale_cloud_microphysics.processes": {
            "values": [
                "cloud droplets", 
                "cloud ice", 
                "effect of raindrops", 
                "effect of snow", 
                "ice nucleation", 
                "mixed phase", 
                "water vapour deposition"
            ]
        }, 
        "cmip6.atmos.microphysics_precipitation.large_scale_cloud_microphysics.scheme_name": {
            "values": [
                "Sakami (2012)"
            ]
        }, 
        "cmip6.atmos.microphysics_precipitation.large_scale_precipitation.hydrometeors": {
            "values": [
                "liquid rain", 
                "snow"
            ]
        }, 
        "cmip6.atmos.microphysics_precipitation.large_scale_precipitation.scheme_name": {
            "values": [
                "Tiedtke (1993)"
            ]
        }, 
        "cmip6.atmos.natural_forcing.insolation_ozone.solar_ozone_impact": {
            "values": [
                true
            ]
        }, 
        "cmip6.atmos.natural_forcing.orbital_parameters.computation_method": {
            "values": [
                "Berger 1978"
            ]
        }, 
        "cmip6.atmos.natural_forcing.orbital_parameters.transient_method": {
            "values": [
                "Obliquity, eccentricity, precession"
            ]
        }, 
        "cmip6.atmos.natural_forcing.orbital_parameters.type": {
            "values": [
                "transient"
            ]
        }, 
        "cmip6.atmos.natural_forcing.solar_constant.transient_characteristics": {
            "values": [
                "Spectral solar insolation provided by SOLARIS is used for historical and future experiments."
            ]
        }, 
        "cmip6.atmos.natural_forcing.solar_constant.type": {
            "values": [
                "transient"
            ]
        }, 
        "cmip6.atmos.observation_simulation.cosp_attributes.number_of_grid_points": {
            "values": [
                51200
            ]
        }, 
        "cmip6.atmos.observation_simulation.cosp_attributes.number_of_levels": {
            "values": [
                40
            ]
        }, 
        "cmip6.atmos.observation_simulation.cosp_attributes.number_of_sub_columns": {
            "values": [
                120
            ]
        }, 
        "cmip6.atmos.observation_simulation.cosp_attributes.run_configuration": {
            "values": [
                "Inline"
            ]
        }, 
        "cmip6.atmos.observation_simulation.isscp_attributes.top_height_direction": {
            "values": [
                "highest altitude level"
            ]
        }, 
        "cmip6.atmos.observation_simulation.isscp_attributes.top_height_estimation_method": {
            "values": [
                "IR brightness", 
                "visible optical depth"
            ]
        }, 
        "cmip6.atmos.observation_simulation.lidar_inputs.ice_types": {
            "values": [
                "ice spheres"
            ]
        }, 
        "cmip6.atmos.observation_simulation.lidar_inputs.overlap": {
            "values": [
                "max"
            ]
        }, 
        "cmip6.atmos.observation_simulation.radar_inputs.effective_radius": {
            "values": [
                true
            ]
        }, 
        "cmip6.atmos.observation_simulation.radar_inputs.frequency": {
            "values": [
                94.0
            ]
        }, 
        "cmip6.atmos.observation_simulation.radar_inputs.gas_absorption": {
            "values": [
                true
            ]
        }, 
        "cmip6.atmos.observation_simulation.radar_inputs.type": {
            "values": [
                "space borne"
            ]
        }, 
        "cmip6.atmos.radiation.aerosols": {
            "values": [
                "Other: black carbon / soot", 
                "dust", 
                "organic", 
                "sea salt", 
                "sulphate"
            ]
        }, 
        "cmip6.atmos.radiation.longwave_radiation.spectral_integration": {
            "values": [
                "wide-band model"
            ]
        }, 
        "cmip6.atmos.radiation.longwave_radiation.spectral_intervals": {
            "values": [
                9
            ]
        }, 
        "cmip6.atmos.radiation.longwave_radiation.transport_calculation": {
            "values": [
                "layer interaction"
            ]
        }, 
        "cmip6.atmos.radiation.shortwave_radiation.spectral_integration": {
            "values": [
                "wide-band model"
            ]
        }, 
        "cmip6.atmos.radiation.shortwave_radiation.spectral_intervals": {
            "values": [
                22
            ]
        }, 
        "cmip6.atmos.turbulence_convection.boundary_layer_turbulence.closure_order": {
            "values": [
                2
            ]
        }, 
        "cmip6.atmos.turbulence_convection.boundary_layer_turbulence.counter_gradient": {
            "values": [
                true
            ]
        }, 
        "cmip6.atmos.turbulence_convection.boundary_layer_turbulence.scheme_name": {
            "values": [
                "Mellor-Yamada"
            ]
        }, 
        "cmip6.atmos.turbulence_convection.boundary_layer_turbulence.scheme_type": {
            "values": [
                "TKE diagnostic"
            ]
        }, 
        "cmip6.atmos.turbulence_convection.deep_convection.processes": {
            "values": [
                "convective momentum transport", 
                "detrainment", 
                "entrainment", 
                "penetrative convection", 
                "updrafts"
            ]
        }, 
        "cmip6.atmos.turbulence_convection.deep_convection.scheme_method": {
            "values": [
                "CAPE"
            ]
        }, 
        "cmip6.atmos.turbulence_convection.deep_convection.scheme_name": {
            "values": [
                "Yoshimura"
            ]
        }, 
        "cmip6.atmos.turbulence_convection.deep_convection.scheme_type": {
            "values": [
                "mass-flux"
            ]
        }, 
        "cmip6.atmos.turbulence_convection.overview": {
            "values": [
                "Microphysics / processes : activation of aerosols\r\n\r\n( MEMO in kakushin model Microphysics :     cloud droplets, effect of rain drops , effect of snow )"
            ]
        }, 
        "cmip6.atmos.turbulence_convection.shallow_convection.scheme_method": {
            "values": [
                "same as deep (unified)"
            ]
        }
    }
}